LICENSE
MANIFEST.in
README.rst
requirements.txt
setup.py
opinel/__init__.py
opinel.egg-info/PKG-INFO
opinel.egg-info/SOURCES.txt
opinel.egg-info/dependency_links.txt
opinel.egg-info/requires.txt
opinel.egg-info/top_level.txt
opinel/data/icmp_message_types.json
opinel/data/protocols.json
opinel/data/requirements.txt
opinel/data/ip-ranges/aws-in-ec2.json
opinel/data/ip-ranges/aws-in-us.json
opinel/data/ip-ranges/aws.json
opinel/services/__init__.py
opinel/services/cloudformation.py
opinel/services/cloudtrail.py
opinel/services/iam.py
opinel/services/organizations.py
opinel/services/s3.py
opinel/utils/__init__.py
opinel/utils/aws.py
opinel/utils/cli_parser.py
opinel/utils/conditions.py
opinel/utils/console.py
opinel/utils/credentials.py
opinel/utils/fs.py
opinel/utils/globals.py
opinel/utils/profiles.py
opinel/utils/threads.py